{"title":"JavaJDBC","slug":"JavaJDBC","date":"2022-12-01","updated":"2022-12-01","comments":true,"path":"api/posts/19301.json","excerpt":"<blockquote><p> 总结了关于 SpringJDBC 连接 SqlServer 和 Mysql</p></blockquote>","cover":null,"covers":null,"content":"<blockquote>\n<p>总结了关于 SpringJDBC 连接 SqlServer 和 Mysql</p>\n</blockquote>\n<span id=\"more\"></span>\n\n<h1 id=\"连接 SqlServer\"><a href=\"# 连接 SqlServer\" class=\"headerlink\" title=\"连接 SqlServer\"></a>连接 SqlServer</h1><blockquote>\n<p>仅仅支持 JDK8,11,17,18</p>\n</blockquote>\n<h2 id=\"导入依赖\"><a href=\"# 导入依赖\" class=\"headerlink\" title=\"导入依赖\"></a>导入依赖</h2><figure class=\"highlight xml\"><table><tr><td class=\"gutter\"><pre><span class=\"line\">1</span><br><span class=\"line\">2</span><br><span class=\"line\">3</span><br><span class=\"line\">4</span><br><span class=\"line\">5</span><br><span class=\"line\">6</span><br><span class=\"line\">7</span><br><span class=\"line\">8</span><br><span class=\"line\">9</span><br><span class=\"line\">10</span><br><span class=\"line\">11</span><br><span class=\"line\">12</span><br><span class=\"line\">13</span><br><span class=\"line\">14</span><br><span class=\"line\">15</span><br><span class=\"line\">16</span><br><span class=\"line\">17</span><br><span class=\"line\">18</span><br><span class=\"line\">19</span><br><span class=\"line\">20</span><br><span class=\"line\">21</span><br><span class=\"line\">22</span><br><span class=\"line\">23</span><br><span class=\"line\">24</span><br><span class=\"line\">25</span><br><span class=\"line\">26</span><br><span class=\"line\">27</span><br><span class=\"line\">28</span><br><span class=\"line\">29</span><br><span class=\"line\">30</span><br><span class=\"line\">31</span><br><span class=\"line\">32</span><br><span class=\"line\">33</span><br><span class=\"line\">34</span><br><span class=\"line\">35</span><br><span class=\"line\">36</span><br><span class=\"line\">37</span><br><span class=\"line\">38</span><br><span class=\"line\">39</span><br></pre></td><td class=\"code\"><pre><span class=\"line\">  <span class=\"tag\">&lt;<span class=\"name\">dependencies</span>&gt;</span></span><br><span class=\"line\"><span class=\"comment\">&lt;!--  junit 版本至少在 4.12 及其以上 --&gt;</span></span><br><span class=\"line\">    <span class=\"tag\">&lt;<span class=\"name\">dependency</span>&gt;</span></span><br><span class=\"line\">      <span class=\"tag\">&lt;<span class=\"name\">groupId</span>&gt;</span>junit<span class=\"tag\">&lt;/<span class=\"name\">groupId</span>&gt;</span></span><br><span class=\"line\">      <span class=\"tag\">&lt;<span class=\"name\">artifactId</span>&gt;</span>junit<span class=\"tag\">&lt;/<span class=\"name\">artifactId</span>&gt;</span></span><br><span class=\"line\">      <span class=\"tag\">&lt;<span class=\"name\">version</span>&gt;</span>4.12<span class=\"tag\">&lt;/<span class=\"name\">version</span>&gt;</span></span><br><span class=\"line\">      <span class=\"tag\">&lt;<span class=\"name\">scope</span>&gt;</span>test<span class=\"tag\">&lt;/<span class=\"name\">scope</span>&gt;</span></span><br><span class=\"line\">    <span class=\"tag\">&lt;/<span class=\"name\">dependency</span>&gt;</span></span><br><span class=\"line\"><span class=\"comment\">&lt;!--    引入 Spring--&gt;</span></span><br><span class=\"line\">    <span class=\"tag\">&lt;<span class=\"name\">dependency</span>&gt;</span></span><br><span class=\"line\">      <span class=\"tag\">&lt;<span class=\"name\">groupId</span>&gt;</span>org.springframework<span class=\"tag\">&lt;/<span class=\"name\">groupId</span>&gt;</span></span><br><span class=\"line\">      <span class=\"tag\">&lt;<span class=\"name\">artifactId</span>&gt;</span>spring-context<span class=\"tag\">&lt;/<span class=\"name\">artifactId</span>&gt;</span></span><br><span class=\"line\">      <span class=\"tag\">&lt;<span class=\"name\">version</span>&gt;</span>5.3.18<span class=\"tag\">&lt;/<span class=\"name\">version</span>&gt;</span></span><br><span class=\"line\">    <span class=\"tag\">&lt;/<span class=\"name\">dependency</span>&gt;</span></span><br><span class=\"line\"><span class=\"comment\">&lt;!--    使用 xml 配置来设置 JDBC 的参数 --&gt;</span></span><br><span class=\"line\">    <span class=\"tag\">&lt;<span class=\"name\">dependency</span>&gt;</span></span><br><span class=\"line\">      <span class=\"tag\">&lt;<span class=\"name\">groupId</span>&gt;</span>org.springframework<span class=\"tag\">&lt;/<span class=\"name\">groupId</span>&gt;</span></span><br><span class=\"line\">      <span class=\"tag\">&lt;<span class=\"name\">artifactId</span>&gt;</span>spring-jdbc<span class=\"tag\">&lt;/<span class=\"name\">artifactId</span>&gt;</span></span><br><span class=\"line\">      <span class=\"tag\">&lt;<span class=\"name\">version</span>&gt;</span>5.3.18<span class=\"tag\">&lt;/<span class=\"name\">version</span>&gt;</span></span><br><span class=\"line\">    <span class=\"tag\">&lt;/<span class=\"name\">dependency</span>&gt;</span></span><br><span class=\"line\"><span class=\"comment\">&lt;!--  模拟 Spring 环境的测试 jar 包 --&gt;</span></span><br><span class=\"line\">    <span class=\"tag\">&lt;<span class=\"name\">dependency</span>&gt;</span></span><br><span class=\"line\">      <span class=\"tag\">&lt;<span class=\"name\">groupId</span>&gt;</span>org.springframework<span class=\"tag\">&lt;/<span class=\"name\">groupId</span>&gt;</span></span><br><span class=\"line\">      <span class=\"tag\">&lt;<span class=\"name\">artifactId</span>&gt;</span>spring-test<span class=\"tag\">&lt;/<span class=\"name\">artifactId</span>&gt;</span></span><br><span class=\"line\">      <span class=\"tag\">&lt;<span class=\"name\">version</span>&gt;</span>5.2.5.RELEASE<span class=\"tag\">&lt;/<span class=\"name\">version</span>&gt;</span></span><br><span class=\"line\">    <span class=\"tag\">&lt;/<span class=\"name\">dependency</span>&gt;</span></span><br><span class=\"line\"><span class=\"comment\">&lt;!-- SQLServer 的连接 jar 包 --&gt;</span></span><br><span class=\"line\">    <span class=\"tag\">&lt;<span class=\"name\">dependency</span>&gt;</span></span><br><span class=\"line\">      <span class=\"tag\">&lt;<span class=\"name\">groupId</span>&gt;</span>com.microsoft.sqlserver<span class=\"tag\">&lt;/<span class=\"name\">groupId</span>&gt;</span></span><br><span class=\"line\">      <span class=\"tag\">&lt;<span class=\"name\">artifactId</span>&gt;</span>mssql-jdbc<span class=\"tag\">&lt;/<span class=\"name\">artifactId</span>&gt;</span></span><br><span class=\"line\">      <span class=\"tag\">&lt;<span class=\"name\">version</span>&gt;</span>7.4.1.jre8<span class=\"tag\">&lt;/<span class=\"name\">version</span>&gt;</span></span><br><span class=\"line\">    <span class=\"tag\">&lt;/<span class=\"name\">dependency</span>&gt;</span></span><br><span class=\"line\"><span class=\"comment\">&lt;!--  使用 C3P0 连接池 --&gt;</span></span><br><span class=\"line\">    <span class=\"tag\">&lt;<span class=\"name\">dependency</span>&gt;</span></span><br><span class=\"line\">      <span class=\"tag\">&lt;<span class=\"name\">groupId</span>&gt;</span>c3p0<span class=\"tag\">&lt;/<span class=\"name\">groupId</span>&gt;</span></span><br><span class=\"line\">      <span class=\"tag\">&lt;<span class=\"name\">artifactId</span>&gt;</span>c3p0<span class=\"tag\">&lt;/<span class=\"name\">artifactId</span>&gt;</span></span><br><span class=\"line\">      <span class=\"tag\">&lt;<span class=\"name\">version</span>&gt;</span>0.9.1.2<span class=\"tag\">&lt;/<span class=\"name\">version</span>&gt;</span></span><br><span class=\"line\">    <span class=\"tag\">&lt;/<span class=\"name\">dependency</span>&gt;</span></span><br><span class=\"line\">  <span class=\"tag\">&lt;/<span class=\"name\">dependencies</span>&gt;</span></span><br></pre></td></tr></table></figure>\n<h2 id=\"配置 applicationContext-xml\"><a href=\"# 配置 applicationContext-xml\" class=\"headerlink\" title=\"配置 applicationContext.xml\"></a>配置 applicationContext.xml</h2><figure class=\"highlight xml\"><table><tr><td class=\"gutter\"><pre><span class=\"line\">1</span><br><span class=\"line\">2</span><br><span class=\"line\">3</span><br><span class=\"line\">4</span><br><span class=\"line\">5</span><br><span class=\"line\">6</span><br><span class=\"line\">7</span><br><span class=\"line\">8</span><br><span class=\"line\">9</span><br><span class=\"line\">10</span><br><span class=\"line\">11</span><br><span class=\"line\">12</span><br><span class=\"line\">13</span><br><span class=\"line\">14</span><br><span class=\"line\">15</span><br><span class=\"line\">16</span><br><span class=\"line\">17</span><br><span class=\"line\">18</span><br><span class=\"line\">19</span><br><span class=\"line\">20</span><br><span class=\"line\">21</span><br><span class=\"line\">22</span><br><span class=\"line\">23</span><br><span class=\"line\">24</span><br><span class=\"line\">25</span><br></pre></td><td class=\"code\"><pre><span class=\"line\"><span class=\"comment\">&lt;!--    1，配置数据源 --&gt;</span></span><br><span class=\"line\">    <span class=\"tag\">&lt;<span class=\"name\">bean</span> <span class=\"attr\">id</span>=<span class=\"string\">&quot;datasource&quot;</span> <span class=\"attr\">class</span>=<span class=\"string\">&quot;com.mchange.v2.c3p0.ComboPooledDataSource&quot;</span>&gt;</span></span><br><span class=\"line\"><span class=\"comment\">&lt;!--        驱动类名，照着写 --&gt;</span></span><br><span class=\"line\">        <span class=\"tag\">&lt;<span class=\"name\">property</span> <span class=\"attr\">name</span>=<span class=\"string\">&quot;driverClass&quot;</span> <span class=\"attr\">value</span>=<span class=\"string\">&quot;com.microsoft.sqlserver.jdbc.SQLServerDriver&quot;</span>/&gt;</span></span><br><span class=\"line\"><span class=\"comment\">&lt;!--        URL 地址，根据自己的 URL 来，端口都是 3306, 主要可能就改个数据库名 --&gt;</span></span><br><span class=\"line\">        <span class=\"tag\">&lt;<span class=\"name\">property</span> <span class=\"attr\">name</span>=<span class=\"string\">&quot;jdbcUrl&quot;</span> <span class=\"attr\">value</span>=<span class=\"string\">&quot;jdbc:sqlserver://localhost:1433;DatabaseName=trding&quot;</span>/&gt;</span></span><br><span class=\"line\"><span class=\"comment\">&lt;!--        登录 sqlserver 数据库的用户名和密码 --&gt;</span></span><br><span class=\"line\">        <span class=\"tag\">&lt;<span class=\"name\">property</span> <span class=\"attr\">name</span>=<span class=\"string\">&quot;user&quot;</span> <span class=\"attr\">value</span>=<span class=\"string\">&quot;sa&quot;</span>/&gt;</span></span><br><span class=\"line\">        <span class=\"tag\">&lt;<span class=\"name\">property</span> <span class=\"attr\">name</span>=<span class=\"string\">&quot;password&quot;</span> <span class=\"attr\">value</span>=<span class=\"string\">&quot;rootxtzl&quot;</span>/&gt;</span></span><br><span class=\"line\">    <span class=\"tag\">&lt;/<span class=\"name\">bean</span>&gt;</span></span><br><span class=\"line\"></span><br><span class=\"line\"></span><br><span class=\"line\"><span class=\"comment\">&lt;!--    2，配置 JDBC 模板 --&gt;</span></span><br><span class=\"line\">    <span class=\"tag\">&lt;<span class=\"name\">bean</span> <span class=\"attr\">id</span>=<span class=\"string\">&quot;jdbcTemplate&quot;</span> <span class=\"attr\">class</span>=<span class=\"string\">&quot;org.springframework.jdbc.core.JdbcTemplate&quot;</span>&gt;</span></span><br><span class=\"line\"><span class=\"comment\">&lt;!--        将我们自己的数据源配置进这个 JDBC 模板 --&gt;</span></span><br><span class=\"line\">        <span class=\"tag\">&lt;<span class=\"name\">property</span> <span class=\"attr\">name</span>=<span class=\"string\">&quot;dataSource&quot;</span> <span class=\"attr\">ref</span>=<span class=\"string\">&quot;datasource&quot;</span>/&gt;</span></span><br><span class=\"line\">    <span class=\"tag\">&lt;/<span class=\"name\">bean</span>&gt;</span></span><br><span class=\"line\"></span><br><span class=\"line\"></span><br><span class=\"line\"></span><br><span class=\"line\"><span class=\"comment\">&lt;!--    3, 注入 JDBC 到具体的 Dao 类 --&gt;</span></span><br><span class=\"line\">    <span class=\"tag\">&lt;<span class=\"name\">bean</span> <span class=\"attr\">id</span>=<span class=\"string\">&quot;userDao&quot;</span> <span class=\"attr\">class</span>=<span class=\"string\">&quot;second.hand.transactions.dao.userDao&quot;</span>&gt;</span></span><br><span class=\"line\"><span class=\"comment\">&lt;!--        将自己配置的 jdbcTempla 注入进具体的 Dao 类 --&gt;</span></span><br><span class=\"line\">        <span class=\"tag\">&lt;<span class=\"name\">property</span> <span class=\"attr\">name</span>=<span class=\"string\">&quot;jdbcTemplate&quot;</span> <span class=\"attr\">ref</span>=<span class=\"string\">&quot;jdbcTemplate&quot;</span>/&gt;</span></span><br><span class=\"line\">    <span class=\"tag\">&lt;/<span class=\"name\">bean</span>&gt;</span></span><br></pre></td></tr></table></figure>\n\n\n<h1 id=\"连接 MySQL\"><a href=\"# 连接 MySQL\" class=\"headerlink\" title=\"连接 MySQL\"></a>连接 MySQL</h1><h2 id=\"引入依赖\"><a href=\"# 引入依赖\" class=\"headerlink\" title=\"引入依赖\"></a>引入依赖</h2><figure class=\"highlight xml\"><table><tr><td class=\"gutter\"><pre><span class=\"line\">1</span><br><span class=\"line\">2</span><br><span class=\"line\">3</span><br><span class=\"line\">4</span><br><span class=\"line\">5</span><br><span class=\"line\">6</span><br><span class=\"line\">7</span><br><span class=\"line\">8</span><br><span class=\"line\">9</span><br><span class=\"line\">10</span><br><span class=\"line\">11</span><br><span class=\"line\">12</span><br><span class=\"line\">13</span><br><span class=\"line\">14</span><br><span class=\"line\">15</span><br><span class=\"line\">16</span><br><span class=\"line\">17</span><br><span class=\"line\">18</span><br><span class=\"line\">19</span><br><span class=\"line\">20</span><br><span class=\"line\">21</span><br><span class=\"line\">22</span><br><span class=\"line\">23</span><br><span class=\"line\">24</span><br><span class=\"line\">25</span><br><span class=\"line\">26</span><br><span class=\"line\">27</span><br><span class=\"line\">28</span><br><span class=\"line\">29</span><br><span class=\"line\">30</span><br><span class=\"line\">31</span><br><span class=\"line\">32</span><br><span class=\"line\">33</span><br><span class=\"line\">34</span><br><span class=\"line\">35</span><br><span class=\"line\">36</span><br><span class=\"line\">37</span><br><span class=\"line\">38</span><br><span class=\"line\">39</span><br><span class=\"line\">40</span><br><span class=\"line\">41</span><br><span class=\"line\">42</span><br><span class=\"line\">43</span><br><span class=\"line\">44</span><br><span class=\"line\">45</span><br><span class=\"line\">46</span><br><span class=\"line\">47</span><br><span class=\"line\">48</span><br></pre></td><td class=\"code\"><pre><span class=\"line\">  <span class=\"tag\">&lt;<span class=\"name\">dependencies</span>&gt;</span></span><br><span class=\"line\">    <span class=\"tag\">&lt;<span class=\"name\">dependency</span>&gt;</span></span><br><span class=\"line\">      <span class=\"tag\">&lt;<span class=\"name\">groupId</span>&gt;</span>junit<span class=\"tag\">&lt;/<span class=\"name\">groupId</span>&gt;</span></span><br><span class=\"line\">      <span class=\"tag\">&lt;<span class=\"name\">artifactId</span>&gt;</span>junit<span class=\"tag\">&lt;/<span class=\"name\">artifactId</span>&gt;</span></span><br><span class=\"line\">      <span class=\"tag\">&lt;<span class=\"name\">version</span>&gt;</span>4.12<span class=\"tag\">&lt;/<span class=\"name\">version</span>&gt;</span></span><br><span class=\"line\">      <span class=\"tag\">&lt;<span class=\"name\">scope</span>&gt;</span>test<span class=\"tag\">&lt;/<span class=\"name\">scope</span>&gt;</span></span><br><span class=\"line\">    <span class=\"tag\">&lt;/<span class=\"name\">dependency</span>&gt;</span></span><br><span class=\"line\"><span class=\"comment\">&lt;!--    引入 Spring--&gt;</span></span><br><span class=\"line\">    <span class=\"tag\">&lt;<span class=\"name\">dependency</span>&gt;</span></span><br><span class=\"line\">      <span class=\"tag\">&lt;<span class=\"name\">groupId</span>&gt;</span>org.springframework<span class=\"tag\">&lt;/<span class=\"name\">groupId</span>&gt;</span></span><br><span class=\"line\">      <span class=\"tag\">&lt;<span class=\"name\">artifactId</span>&gt;</span>spring-context<span class=\"tag\">&lt;/<span class=\"name\">artifactId</span>&gt;</span></span><br><span class=\"line\">      <span class=\"tag\">&lt;<span class=\"name\">version</span>&gt;</span>5.3.18<span class=\"tag\">&lt;/<span class=\"name\">version</span>&gt;</span></span><br><span class=\"line\">    <span class=\"tag\">&lt;/<span class=\"name\">dependency</span>&gt;</span></span><br><span class=\"line\"><span class=\"comment\">&lt;!--    使用 xml 配置来设置 JDBC 的参数 --&gt;</span></span><br><span class=\"line\">    <span class=\"tag\">&lt;<span class=\"name\">dependency</span>&gt;</span></span><br><span class=\"line\">      <span class=\"tag\">&lt;<span class=\"name\">groupId</span>&gt;</span>org.springframework<span class=\"tag\">&lt;/<span class=\"name\">groupId</span>&gt;</span></span><br><span class=\"line\">      <span class=\"tag\">&lt;<span class=\"name\">artifactId</span>&gt;</span>spring-jdbc<span class=\"tag\">&lt;/<span class=\"name\">artifactId</span>&gt;</span></span><br><span class=\"line\">      <span class=\"tag\">&lt;<span class=\"name\">version</span>&gt;</span>5.3.18<span class=\"tag\">&lt;/<span class=\"name\">version</span>&gt;</span></span><br><span class=\"line\">    <span class=\"tag\">&lt;/<span class=\"name\">dependency</span>&gt;</span></span><br><span class=\"line\"><span class=\"comment\">&lt;!--  模拟 Spring 环境的测试 jar 包 --&gt;</span></span><br><span class=\"line\">    <span class=\"tag\">&lt;<span class=\"name\">dependency</span>&gt;</span></span><br><span class=\"line\">      <span class=\"tag\">&lt;<span class=\"name\">groupId</span>&gt;</span>org.springframework<span class=\"tag\">&lt;/<span class=\"name\">groupId</span>&gt;</span></span><br><span class=\"line\">      <span class=\"tag\">&lt;<span class=\"name\">artifactId</span>&gt;</span>spring-test<span class=\"tag\">&lt;/<span class=\"name\">artifactId</span>&gt;</span></span><br><span class=\"line\">      <span class=\"tag\">&lt;<span class=\"name\">version</span>&gt;</span>5.2.5.RELEASE<span class=\"tag\">&lt;/<span class=\"name\">version</span>&gt;</span></span><br><span class=\"line\">    <span class=\"tag\">&lt;/<span class=\"name\">dependency</span>&gt;</span></span><br><span class=\"line\"></span><br><span class=\"line\"><span class=\"comment\">&lt;!--    使用 MySQL 8.X 的连接包 --&gt;</span></span><br><span class=\"line\">    <span class=\"tag\">&lt;<span class=\"name\">dependency</span>&gt;</span></span><br><span class=\"line\">      <span class=\"tag\">&lt;<span class=\"name\">groupId</span>&gt;</span>mysql<span class=\"tag\">&lt;/<span class=\"name\">groupId</span>&gt;</span></span><br><span class=\"line\">      <span class=\"tag\">&lt;<span class=\"name\">artifactId</span>&gt;</span>mysql-connector-java<span class=\"tag\">&lt;/<span class=\"name\">artifactId</span>&gt;</span></span><br><span class=\"line\">      <span class=\"tag\">&lt;<span class=\"name\">version</span>&gt;</span>8.0.21<span class=\"tag\">&lt;/<span class=\"name\">version</span>&gt;</span></span><br><span class=\"line\">    <span class=\"tag\">&lt;/<span class=\"name\">dependency</span>&gt;</span></span><br><span class=\"line\"></span><br><span class=\"line\"><span class=\"comment\">&lt;!--    MySQL5.X 的驱动包 --&gt;</span></span><br><span class=\"line\"><span class=\"comment\">&lt;!--    &lt;dependency&gt;--&gt;</span></span><br><span class=\"line\"><span class=\"comment\">&lt;!--      &lt;groupId&gt;mysql&lt;/groupId&gt;--&gt;</span></span><br><span class=\"line\"><span class=\"comment\">&lt;!--      &lt;artifactId&gt;mysql-connector-java&lt;/artifactId&gt;--&gt;</span></span><br><span class=\"line\"><span class=\"comment\">&lt;!--      &lt;version&gt;5.1.49&lt;/version&gt;--&gt;</span></span><br><span class=\"line\"><span class=\"comment\">&lt;!--    &lt;/dependency&gt;--&gt;</span></span><br><span class=\"line\"></span><br><span class=\"line\">    <span class=\"comment\">&lt;!--  使用 C3P0 连接池 --&gt;</span></span><br><span class=\"line\">    <span class=\"tag\">&lt;<span class=\"name\">dependency</span>&gt;</span></span><br><span class=\"line\">      <span class=\"tag\">&lt;<span class=\"name\">groupId</span>&gt;</span>c3p0<span class=\"tag\">&lt;/<span class=\"name\">groupId</span>&gt;</span></span><br><span class=\"line\">      <span class=\"tag\">&lt;<span class=\"name\">artifactId</span>&gt;</span>c3p0<span class=\"tag\">&lt;/<span class=\"name\">artifactId</span>&gt;</span></span><br><span class=\"line\">      <span class=\"tag\">&lt;<span class=\"name\">version</span>&gt;</span>0.9.1.2<span class=\"tag\">&lt;/<span class=\"name\">version</span>&gt;</span></span><br><span class=\"line\">    <span class=\"tag\">&lt;/<span class=\"name\">dependency</span>&gt;</span></span><br><span class=\"line\">  <span class=\"tag\">&lt;/<span class=\"name\">dependencies</span>&gt;</span></span><br><span class=\"line\"></span><br></pre></td></tr></table></figure>\n\n<h2 id=\"配置数据源等实例 -application-xml\"><a href=\"# 配置数据源等实例 -application-xml\" class=\"headerlink\" title=\"配置数据源等实例 (application.xml)\"></a> 配置数据源等实例(application.xml)</h2><figure class=\"highlight xml\"><table><tr><td class=\"gutter\"><pre><span class=\"line\">1</span><br><span class=\"line\">2</span><br><span class=\"line\">3</span><br><span class=\"line\">4</span><br><span class=\"line\">5</span><br><span class=\"line\">6</span><br><span class=\"line\">7</span><br><span class=\"line\">8</span><br><span class=\"line\">9</span><br><span class=\"line\">10</span><br><span class=\"line\">11</span><br><span class=\"line\">12</span><br><span class=\"line\">13</span><br><span class=\"line\">14</span><br><span class=\"line\">15</span><br><span class=\"line\">16</span><br><span class=\"line\">17</span><br><span class=\"line\">18</span><br><span class=\"line\">19</span><br><span class=\"line\">20</span><br><span class=\"line\">21</span><br><span class=\"line\">22</span><br><span class=\"line\">23</span><br><span class=\"line\">24</span><br><span class=\"line\">25</span><br><span class=\"line\">26</span><br><span class=\"line\">27</span><br><span class=\"line\">28</span><br><span class=\"line\">29</span><br></pre></td><td class=\"code\"><pre><span class=\"line\"><span class=\"meta\">&lt;?xml version=<span class=\"string\">&quot;1.0&quot;</span> encoding=<span class=\"string\">&quot;UTF-8&quot;</span>?&gt;</span></span><br><span class=\"line\"><span class=\"tag\">&lt;<span class=\"name\">beans</span> <span class=\"attr\">xmlns</span>=<span class=\"string\">&quot;http://www.springframework.org/schema/beans&quot;</span></span></span><br><span class=\"line\"><span class=\"tag\">       <span class=\"attr\">xmlns:xsi</span>=<span class=\"string\">&quot;http://www.w3.org/2001/XMLSchema-instance&quot;</span></span></span><br><span class=\"line\"><span class=\"tag\">       <span class=\"attr\">xsi:schemaLocation</span>=<span class=\"string\">&quot;http://www.springframework.org/schema/beans http://www.springframework.org/schema/beans/spring-beans.xsd&quot;</span>&gt;</span></span><br><span class=\"line\"><span class=\"comment\">&lt;!--    1，配置数据源 --&gt;</span></span><br><span class=\"line\">    <span class=\"tag\">&lt;<span class=\"name\">bean</span> <span class=\"attr\">id</span>=<span class=\"string\">&quot;datasource&quot;</span> <span class=\"attr\">class</span>=<span class=\"string\">&quot;com.mchange.v2.c3p0.ComboPooledDataSource&quot;</span>&gt;</span></span><br><span class=\"line\"><span class=\"comment\">&lt;!--        驱动类名，照着写 --&gt;</span></span><br><span class=\"line\">        <span class=\"tag\">&lt;<span class=\"name\">property</span> <span class=\"attr\">name</span>=<span class=\"string\">&quot;driverClass&quot;</span> <span class=\"attr\">value</span>=<span class=\"string\">&quot;com.mysql.cj.jdbc.Driver&quot;</span>/&gt;</span></span><br><span class=\"line\"><span class=\"comment\">&lt;!--        URL 地址，根据自己的 URL 来，端口都是 3306, 主要可能就改个数据库名 --&gt;</span></span><br><span class=\"line\">        <span class=\"tag\">&lt;<span class=\"name\">property</span> <span class=\"attr\">name</span>=<span class=\"string\">&quot;jdbcUrl&quot;</span> <span class=\"attr\">value</span>=<span class=\"string\">&quot;jdbc:mysql://localhost:3306/triding?serverTimezone=UTC&quot;</span>/&gt;</span></span><br><span class=\"line\"><span class=\"comment\">&lt;!--        登录 sqlserver 数据库的用户名和密码 --&gt;</span></span><br><span class=\"line\">        <span class=\"tag\">&lt;<span class=\"name\">property</span> <span class=\"attr\">name</span>=<span class=\"string\">&quot;user&quot;</span> <span class=\"attr\">value</span>=<span class=\"string\">&quot;root&quot;</span>/&gt;</span></span><br><span class=\"line\">        <span class=\"tag\">&lt;<span class=\"name\">property</span> <span class=\"attr\">name</span>=<span class=\"string\">&quot;password&quot;</span> <span class=\"attr\">value</span>=<span class=\"string\">&quot;root&quot;</span>/&gt;</span></span><br><span class=\"line\">    <span class=\"tag\">&lt;/<span class=\"name\">bean</span>&gt;</span></span><br><span class=\"line\"></span><br><span class=\"line\"></span><br><span class=\"line\"><span class=\"comment\">&lt;!--    2，配置 JDBC 模板 --&gt;</span></span><br><span class=\"line\">    <span class=\"tag\">&lt;<span class=\"name\">bean</span> <span class=\"attr\">id</span>=<span class=\"string\">&quot;jdbcTemplate&quot;</span> <span class=\"attr\">class</span>=<span class=\"string\">&quot;org.springframework.jdbc.core.JdbcTemplate&quot;</span>&gt;</span></span><br><span class=\"line\"><span class=\"comment\">&lt;!--        将我们自己的数据源配置进这个 JDBC 模板 --&gt;</span></span><br><span class=\"line\">        <span class=\"tag\">&lt;<span class=\"name\">property</span> <span class=\"attr\">name</span>=<span class=\"string\">&quot;dataSource&quot;</span> <span class=\"attr\">ref</span>=<span class=\"string\">&quot;datasource&quot;</span>/&gt;</span></span><br><span class=\"line\">    <span class=\"tag\">&lt;/<span class=\"name\">bean</span>&gt;</span></span><br><span class=\"line\"></span><br><span class=\"line\"></span><br><span class=\"line\"><span class=\"comment\">&lt;!--    3, 注入 JDBC 到具体的 Dao 类 --&gt;</span></span><br><span class=\"line\">    <span class=\"tag\">&lt;<span class=\"name\">bean</span> <span class=\"attr\">id</span>=<span class=\"string\">&quot;userDao&quot;</span> <span class=\"attr\">class</span>=<span class=\"string\">&quot;second.hand.transactions.dao.userDao&quot;</span>&gt;</span></span><br><span class=\"line\"><span class=\"comment\">&lt;!--        将自己配置的 jdbcTempla 注入进具体的 Dao 类 --&gt;</span></span><br><span class=\"line\">        <span class=\"tag\">&lt;<span class=\"name\">property</span> <span class=\"attr\">name</span>=<span class=\"string\">&quot;jdbcTemplate&quot;</span> <span class=\"attr\">ref</span>=<span class=\"string\">&quot;jdbcTemplate&quot;</span>/&gt;</span></span><br><span class=\"line\">    <span class=\"tag\">&lt;/<span class=\"name\">bean</span>&gt;</span></span><br><span class=\"line\"><span class=\"tag\">&lt;/<span class=\"name\">beans</span>&gt;</span></span><br></pre></td></tr></table></figure>\n\n\n<h1 id=\"实体类 User\"><a href=\"# 实体类 User\" class=\"headerlink\" title=\"实体类 User\"></a>实体类 User</h1><figure class=\"highlight java\"><table><tr><td class=\"gutter\"><pre><span class=\"line\">1</span><br><span class=\"line\">2</span><br><span class=\"line\">3</span><br><span class=\"line\">4</span><br><span class=\"line\">5</span><br><span class=\"line\">6</span><br><span class=\"line\">7</span><br><span class=\"line\">8</span><br><span class=\"line\">9</span><br><span class=\"line\">10</span><br><span class=\"line\">11</span><br><span class=\"line\">12</span><br><span class=\"line\">13</span><br><span class=\"line\">14</span><br><span class=\"line\">15</span><br><span class=\"line\">16</span><br><span class=\"line\">17</span><br><span class=\"line\">18</span><br><span class=\"line\">19</span><br><span class=\"line\">20</span><br><span class=\"line\">21</span><br><span class=\"line\">22</span><br><span class=\"line\">23</span><br><span class=\"line\">24</span><br><span class=\"line\">25</span><br><span class=\"line\">26</span><br><span class=\"line\">27</span><br><span class=\"line\">28</span><br><span class=\"line\">29</span><br><span class=\"line\">30</span><br><span class=\"line\">31</span><br><span class=\"line\">32</span><br><span class=\"line\">33</span><br><span class=\"line\">34</span><br><span class=\"line\">35</span><br><span class=\"line\">36</span><br><span class=\"line\">37</span><br><span class=\"line\">38</span><br><span class=\"line\">39</span><br><span class=\"line\">40</span><br><span class=\"line\">41</span><br><span class=\"line\">42</span><br><span class=\"line\">43</span><br><span class=\"line\">44</span><br><span class=\"line\">45</span><br><span class=\"line\">46</span><br><span class=\"line\">47</span><br><span class=\"line\">48</span><br><span class=\"line\">49</span><br><span class=\"line\">50</span><br><span class=\"line\">51</span><br><span class=\"line\">52</span><br><span class=\"line\">53</span><br><span class=\"line\">54</span><br><span class=\"line\">55</span><br><span class=\"line\">56</span><br><span class=\"line\">57</span><br><span class=\"line\">58</span><br><span class=\"line\">59</span><br><span class=\"line\">60</span><br><span class=\"line\">61</span><br><span class=\"line\">62</span><br><span class=\"line\">63</span><br><span class=\"line\">64</span><br><span class=\"line\">65</span><br><span class=\"line\">66</span><br><span class=\"line\">67</span><br><span class=\"line\">68</span><br><span class=\"line\">69</span><br><span class=\"line\">70</span><br><span class=\"line\">71</span><br><span class=\"line\">72</span><br><span class=\"line\">73</span><br><span class=\"line\">74</span><br><span class=\"line\">75</span><br><span class=\"line\">76</span><br><span class=\"line\">77</span><br><span class=\"line\">78</span><br><span class=\"line\">79</span><br><span class=\"line\">80</span><br><span class=\"line\">81</span><br><span class=\"line\">82</span><br><span class=\"line\">83</span><br><span class=\"line\">84</span><br><span class=\"line\">85</span><br><span class=\"line\">86</span><br><span class=\"line\">87</span><br><span class=\"line\">88</span><br><span class=\"line\">89</span><br><span class=\"line\">90</span><br><span class=\"line\">91</span><br><span class=\"line\">92</span><br><span class=\"line\">93</span><br><span class=\"line\">94</span><br><span class=\"line\">95</span><br><span class=\"line\">96</span><br><span class=\"line\">97</span><br><span class=\"line\">98</span><br><span class=\"line\">99</span><br><span class=\"line\">100</span><br><span class=\"line\">101</span><br><span class=\"line\">102</span><br><span class=\"line\">103</span><br><span class=\"line\">104</span><br><span class=\"line\">105</span><br><span class=\"line\">106</span><br><span class=\"line\">107</span><br></pre></td><td class=\"code\"><pre><span class=\"line\"><span class=\"keyword\">package</span> second.hand.transactions.entities;</span><br><span class=\"line\"></span><br><span class=\"line\"><span class=\"keyword\">import</span> java.io.Serializable;</span><br><span class=\"line\"></span><br><span class=\"line\"><span class=\"comment\">/**</span></span><br><span class=\"line\"><span class=\"comment\"> * <span class=\"doctag\">@author</span> Wente</span></span><br><span class=\"line\"><span class=\"comment\"> * <span class=\"doctag\">@date</span> 2022/11/30</span></span><br><span class=\"line\"><span class=\"comment\"> * 普通用户类</span></span><br><span class=\"line\"><span class=\"comment\"> **/</span></span><br><span class=\"line\"><span class=\"keyword\">public</span> <span class=\"keyword\">class</span> <span class=\"title class_\">User</span> <span class=\"keyword\">implements</span> <span class=\"title class_\">Serializable</span> &#123;</span><br><span class=\"line\">    <span class=\"keyword\">private</span> Long userId;</span><br><span class=\"line\">    <span class=\"keyword\">private</span> Long carId;</span><br><span class=\"line\">    <span class=\"keyword\">private</span> String userName;</span><br><span class=\"line\">    <span class=\"keyword\">private</span> String userPwd;</span><br><span class=\"line\">    <span class=\"keyword\">private</span> String userNickname;</span><br><span class=\"line\">    <span class=\"keyword\">private</span> String userBirth;</span><br><span class=\"line\">    <span class=\"keyword\">private</span> String userPsig;</span><br><span class=\"line\">    <span class=\"keyword\">private</span> String userQq;</span><br><span class=\"line\">    <span class=\"keyword\">private</span> String userTele;</span><br><span class=\"line\"></span><br><span class=\"line\">    <span class=\"meta\">@Override</span></span><br><span class=\"line\">    <span class=\"keyword\">public</span> String <span class=\"title function_\">toString</span><span class=\"params\">()</span> &#123;</span><br><span class=\"line\">        <span class=\"keyword\">return</span> <span class=\"string\">&quot;User&#123;&quot;</span> +</span><br><span class=\"line\">                <span class=\"string\">&quot;userId=&quot;</span> + userId +</span><br><span class=\"line\">                <span class=\"string\">&quot;, carId=&quot;</span> + carId +</span><br><span class=\"line\">                <span class=\"string\">&quot;, userName=&#x27;&quot;</span> + userName + <span class=\"string\">&#x27;\\&#x27;&#x27;</span> +</span><br><span class=\"line\">                <span class=\"string\">&quot;, userPwd=&#x27;&quot;</span> + userPwd + <span class=\"string\">&#x27;\\&#x27;&#x27;</span> +</span><br><span class=\"line\">                <span class=\"string\">&quot;, userNickname=&#x27;&quot;</span> + userNickname + <span class=\"string\">&#x27;\\&#x27;&#x27;</span> +</span><br><span class=\"line\">                <span class=\"string\">&quot;, userBirth=&#x27;&quot;</span> + userBirth + <span class=\"string\">&#x27;\\&#x27;&#x27;</span> +</span><br><span class=\"line\">                <span class=\"string\">&quot;, userPsig=&#x27;&quot;</span> + userPsig + <span class=\"string\">&#x27;\\&#x27;&#x27;</span> +</span><br><span class=\"line\">                <span class=\"string\">&quot;, userQq=&#x27;&quot;</span> + userQq + <span class=\"string\">&#x27;\\&#x27;&#x27;</span> +</span><br><span class=\"line\">                <span class=\"string\">&quot;, userTele=&#x27;&quot;</span> + userTele + <span class=\"string\">&#x27;\\&#x27;&#x27;</span> +</span><br><span class=\"line\">                <span class=\"string\">&#x27;&#125;&#x27;</span>;</span><br><span class=\"line\">    &#125;</span><br><span class=\"line\"></span><br><span class=\"line\">    <span class=\"keyword\">public</span> Long <span class=\"title function_\">getUserId</span><span class=\"params\">()</span> &#123;</span><br><span class=\"line\">        <span class=\"keyword\">return</span> userId;</span><br><span class=\"line\">    &#125;</span><br><span class=\"line\"></span><br><span class=\"line\">    <span class=\"keyword\">public</span> <span class=\"keyword\">void</span> <span class=\"title function_\">setUserId</span><span class=\"params\">(Long userId)</span> &#123;</span><br><span class=\"line\">        <span class=\"built_in\">this</span>.userId = userId;</span><br><span class=\"line\">    &#125;</span><br><span class=\"line\"></span><br><span class=\"line\">    <span class=\"keyword\">public</span> Long <span class=\"title function_\">getCarId</span><span class=\"params\">()</span> &#123;</span><br><span class=\"line\">        <span class=\"keyword\">return</span> carId;</span><br><span class=\"line\">    &#125;</span><br><span class=\"line\"></span><br><span class=\"line\">    <span class=\"keyword\">public</span> <span class=\"keyword\">void</span> <span class=\"title function_\">setCarId</span><span class=\"params\">(Long carId)</span> &#123;</span><br><span class=\"line\">        <span class=\"built_in\">this</span>.carId = carId;</span><br><span class=\"line\">    &#125;</span><br><span class=\"line\"></span><br><span class=\"line\">    <span class=\"keyword\">public</span> String <span class=\"title function_\">getUserName</span><span class=\"params\">()</span> &#123;</span><br><span class=\"line\">        <span class=\"keyword\">return</span> userName;</span><br><span class=\"line\">    &#125;</span><br><span class=\"line\"></span><br><span class=\"line\">    <span class=\"keyword\">public</span> <span class=\"keyword\">void</span> <span class=\"title function_\">setUserName</span><span class=\"params\">(String userName)</span> &#123;</span><br><span class=\"line\">        <span class=\"built_in\">this</span>.userName = userName;</span><br><span class=\"line\">    &#125;</span><br><span class=\"line\"></span><br><span class=\"line\">    <span class=\"keyword\">public</span> String <span class=\"title function_\">getUserPwd</span><span class=\"params\">()</span> &#123;</span><br><span class=\"line\">        <span class=\"keyword\">return</span> userPwd;</span><br><span class=\"line\">    &#125;</span><br><span class=\"line\"></span><br><span class=\"line\">    <span class=\"keyword\">public</span> <span class=\"keyword\">void</span> <span class=\"title function_\">setUserPwd</span><span class=\"params\">(String userPwd)</span> &#123;</span><br><span class=\"line\">        <span class=\"built_in\">this</span>.userPwd = userPwd;</span><br><span class=\"line\">    &#125;</span><br><span class=\"line\"></span><br><span class=\"line\">    <span class=\"keyword\">public</span> String <span class=\"title function_\">getUserNickname</span><span class=\"params\">()</span> &#123;</span><br><span class=\"line\">        <span class=\"keyword\">return</span> userNickname;</span><br><span class=\"line\">    &#125;</span><br><span class=\"line\"></span><br><span class=\"line\">    <span class=\"keyword\">public</span> <span class=\"keyword\">void</span> <span class=\"title function_\">setUserNickname</span><span class=\"params\">(String userNickname)</span> &#123;</span><br><span class=\"line\">        <span class=\"built_in\">this</span>.userNickname = userNickname;</span><br><span class=\"line\">    &#125;</span><br><span class=\"line\"></span><br><span class=\"line\">    <span class=\"keyword\">public</span> String <span class=\"title function_\">getUserBirth</span><span class=\"params\">()</span> &#123;</span><br><span class=\"line\">        <span class=\"keyword\">return</span> userBirth;</span><br><span class=\"line\">    &#125;</span><br><span class=\"line\"></span><br><span class=\"line\">    <span class=\"keyword\">public</span> <span class=\"keyword\">void</span> <span class=\"title function_\">setUserBirth</span><span class=\"params\">(String userBirth)</span> &#123;</span><br><span class=\"line\">        <span class=\"built_in\">this</span>.userBirth = userBirth;</span><br><span class=\"line\">    &#125;</span><br><span class=\"line\"></span><br><span class=\"line\">    <span class=\"keyword\">public</span> String <span class=\"title function_\">getUserPsig</span><span class=\"params\">()</span> &#123;</span><br><span class=\"line\">        <span class=\"keyword\">return</span> userPsig;</span><br><span class=\"line\">    &#125;</span><br><span class=\"line\"></span><br><span class=\"line\">    <span class=\"keyword\">public</span> <span class=\"keyword\">void</span> <span class=\"title function_\">setUserPsig</span><span class=\"params\">(String userPsig)</span> &#123;</span><br><span class=\"line\">        <span class=\"built_in\">this</span>.userPsig = userPsig;</span><br><span class=\"line\">    &#125;</span><br><span class=\"line\"></span><br><span class=\"line\">    <span class=\"keyword\">public</span> String <span class=\"title function_\">getUserQq</span><span class=\"params\">()</span> &#123;</span><br><span class=\"line\">        <span class=\"keyword\">return</span> userQq;</span><br><span class=\"line\">    &#125;</span><br><span class=\"line\"></span><br><span class=\"line\">    <span class=\"keyword\">public</span> <span class=\"keyword\">void</span> <span class=\"title function_\">setUserQq</span><span class=\"params\">(String userQq)</span> &#123;</span><br><span class=\"line\">        <span class=\"built_in\">this</span>.userQq = userQq;</span><br><span class=\"line\">    &#125;</span><br><span class=\"line\"></span><br><span class=\"line\">    <span class=\"keyword\">public</span> String <span class=\"title function_\">getUserTele</span><span class=\"params\">()</span> &#123;</span><br><span class=\"line\">        <span class=\"keyword\">return</span> userTele;</span><br><span class=\"line\">    &#125;</span><br><span class=\"line\"></span><br><span class=\"line\">    <span class=\"keyword\">public</span> <span class=\"keyword\">void</span> <span class=\"title function_\">setUserTele</span><span class=\"params\">(String userTele)</span> &#123;</span><br><span class=\"line\">        <span class=\"built_in\">this</span>.userTele = userTele;</span><br><span class=\"line\">    &#125;</span><br><span class=\"line\">&#125;</span><br></pre></td></tr></table></figure>\n\n<h1 id=\"userDao- 与数据库交互用的模板类\"><a href=\"#userDao- 与数据库交互用的模板类\" class=\"headerlink\" title=\"userDao(与数据库交互用的模板类)\"></a>userDao(与数据库交互用的模板类)</h1><figure class=\"highlight java\"><table><tr><td class=\"gutter\"><pre><span class=\"line\">1</span><br><span class=\"line\">2</span><br><span class=\"line\">3</span><br><span class=\"line\">4</span><br><span class=\"line\">5</span><br><span class=\"line\">6</span><br><span class=\"line\">7</span><br><span class=\"line\">8</span><br><span class=\"line\">9</span><br><span class=\"line\">10</span><br><span class=\"line\">11</span><br><span class=\"line\">12</span><br><span class=\"line\">13</span><br><span class=\"line\">14</span><br><span class=\"line\">15</span><br><span class=\"line\">16</span><br><span class=\"line\">17</span><br><span class=\"line\">18</span><br><span class=\"line\">19</span><br><span class=\"line\">20</span><br><span class=\"line\">21</span><br><span class=\"line\">22</span><br></pre></td><td class=\"code\"><pre><span class=\"line\"><span class=\"keyword\">public</span> <span class=\"keyword\">class</span> <span class=\"title class_\">userDao</span> &#123;</span><br><span class=\"line\"></span><br><span class=\"line\">    <span class=\"keyword\">private</span> JdbcTemplate jdbcTemplate;</span><br><span class=\"line\"></span><br><span class=\"line\">    <span class=\"keyword\">public</span> JdbcTemplate <span class=\"title function_\">getJdbcTemplate</span><span class=\"params\">()</span> &#123;</span><br><span class=\"line\">        <span class=\"keyword\">return</span> jdbcTemplate;</span><br><span class=\"line\">    &#125;</span><br><span class=\"line\"></span><br><span class=\"line\">    <span class=\"keyword\">public</span> <span class=\"keyword\">void</span> <span class=\"title function_\">setJdbcTemplate</span><span class=\"params\">(JdbcTemplate jdbcTemplate)</span> &#123;</span><br><span class=\"line\">        <span class=\"built_in\">this</span>.jdbcTemplate = jdbcTemplate;</span><br><span class=\"line\">    &#125;</span><br><span class=\"line\"></span><br><span class=\"line\">    <span class=\"comment\">/**</span></span><br><span class=\"line\"><span class=\"comment\">     * 向数据库中添加数据</span></span><br><span class=\"line\"><span class=\"comment\">     */</span></span><br><span class=\"line\">    <span class=\"keyword\">public</span> <span class=\"keyword\">void</span> <span class=\"title function_\">addUserCommon</span><span class=\"params\">()</span>&#123;</span><br><span class=\"line\">        <span class=\"type\">String</span> <span class=\"variable\">sql</span> <span class=\"operator\">=</span> <span class=\"string\">&quot;insert into user_common(user_id,user_name,user_pwd,user_nickname,user_birth,user_psig,user_qq,user_tele)values(42000,&#x27;wente&#x27;,&#x27;wenteroot&#x27;,&#x27; 文特 &#x27;,&#x27;2001/12/05&#x27;,&#x27; 个性签名 &#x27;,&#x27;393815277&#x27;,&#x27;18423225933&#x27;)&quot;</span>;</span><br><span class=\"line\">        <span class=\"comment\">// 返回 updateResult 表示受影响的行数</span></span><br><span class=\"line\">        <span class=\"type\">int</span> <span class=\"variable\">updateResult</span> <span class=\"operator\">=</span> jdbcTemplate.update(sql);</span><br><span class=\"line\">        System.out.println(updateResult);</span><br><span class=\"line\">    &#125;</span><br><span class=\"line\">&#125;</span><br></pre></td></tr></table></figure>\n<h1 id=\"测试类\"><a href=\"# 测试类\" class=\"headerlink\" title=\"测试类\"></a>测试类</h1><figure class=\"highlight java\"><table><tr><td class=\"gutter\"><pre><span class=\"line\">1</span><br><span class=\"line\">2</span><br><span class=\"line\">3</span><br><span class=\"line\">4</span><br><span class=\"line\">5</span><br><span class=\"line\">6</span><br><span class=\"line\">7</span><br><span class=\"line\">8</span><br><span class=\"line\">9</span><br><span class=\"line\">10</span><br><span class=\"line\">11</span><br><span class=\"line\">12</span><br><span class=\"line\">13</span><br></pre></td><td class=\"code\"><pre><span class=\"line\"><span class=\"comment\">// 注解是用来配置 Spring 的测试环境</span></span><br><span class=\"line\"><span class=\"meta\">@ContextConfiguration(&quot;classpath:applicationContext.xml&quot;)</span></span><br><span class=\"line\"><span class=\"meta\">@RunWith(SpringJUnit4ClassRunner.class)</span></span><br><span class=\"line\"><span class=\"keyword\">public</span> <span class=\"keyword\">class</span> <span class=\"title class_\">TestUser</span> &#123;</span><br><span class=\"line\">    <span class=\"meta\">@Test</span></span><br><span class=\"line\">    <span class=\"keyword\">public</span> <span class=\"keyword\">void</span> <span class=\"title function_\">test1</span><span class=\"params\">()</span>&#123;</span><br><span class=\"line\">        <span class=\"comment\">// 获取 userDao 的实例</span></span><br><span class=\"line\">        <span class=\"type\">ApplicationContext</span> <span class=\"variable\">ctx</span> <span class=\"operator\">=</span> <span class=\"keyword\">new</span> <span class=\"title class_\">ClassPathXmlApplicationContext</span>(<span class=\"string\">&quot;applicationContext.xml&quot;</span>);</span><br><span class=\"line\">        <span class=\"type\">userDao</span> <span class=\"variable\">userDao</span> <span class=\"operator\">=</span> (userDao) ctx.getBean(<span class=\"string\">&quot;userDao&quot;</span>);</span><br><span class=\"line\">        <span class=\"comment\">// 执行添加用户方法, 该方法是我们自定义的</span></span><br><span class=\"line\">        userDao.addUserCommon();</span><br><span class=\"line\">    &#125;</span><br><span class=\"line\">&#125;</span><br></pre></td></tr></table></figure>","url":"/posts/19301/","min2read":9,"word4post":"1.6k","prev_post":null,"next_post":{"title":"ssm_beanXml","url":"/posts/12964/"},"toc":"<ol class=\"toc\"><li class=\"toc-item toc-level-1\"><a class=\"toc-link\" data-id=\"连接 SqlServer\" href = \"#\"><span class=\"toc-number\">1.</span> <span class=\"toc-text\">连接 SqlServer</span></a><ol class=\"toc-child\"><li class=\"toc-item toc-level-2\"><a class=\"toc-link\" data-id=\"导入依赖\" href = \"#\"><span class=\"toc-number\">1.1.</span> <span class=\"toc-text\">导入依赖</span></a></li><li class=\"toc-item toc-level-2\"><a class=\"toc-link\" data-id=\"配置 applicationContext-xml\" href = \"#\"><span class=\"toc-number\">1.2.</span> <span class=\"toc-text\">配置 applicationContext.xml</span></a></li></ol></li><li class=\"toc-item toc-level-1\"><a class=\"toc-link\" data-id=\"连接 MySQL\" href = \"#\"><span class=\"toc-number\">2.</span> <span class=\"toc-text\">连接 MySQL</span></a><ol class=\"toc-child\"><li class=\"toc-item toc-level-2\"><a class=\"toc-link\" data-id=\"引入依赖\" href = \"#\"><span class=\"toc-number\">2.1.</span> <span class=\"toc-text\">引入依赖</span></a></li><li class=\"toc-item toc-level-2\"><a class=\"toc-link\" data-id=\"配置数据源等实例 -application-xml\" href = \"#\"><span class=\"toc-number\">2.2.</span> <span class=\"toc-text\"> 配置数据源等实例(application.xml)</span></a></li></ol></li><li class=\"toc-item toc-level-1\"><a class=\"toc-link\" data-id=\"实体类 User\" href = \"#\"><span class=\"toc-number\">3.</span> <span class=\"toc-text\">实体类 User</span></a></li><li class=\"toc-item toc-level-1\"><a class=\"toc-link\" data-id=\"userDao- 与数据库交互用的模板类\" href = \"#\"><span class=\"toc-number\">4.</span> <span class=\"toc-text\">userDao(与数据库交互用的模板类)</span></a></li><li class=\"toc-item toc-level-1\"><a class=\"toc-link\" data-id=\"测试类\" href = \"#\"><span class=\"toc-number\">5.</span> <span class=\"toc-text\">测试类</span></a></li></ol>","categories":[{"name":"JavaStudy","path":"api/categories/JavaStudy.json","url":"/categories/JavaStudy/"}],"tags":[{"name":"SpringJDBC","path":"api/tags/SpringJDBC.json","url":"/tags/SpringJDBC/"}]}