{"name":"Mabtis","postlist":[{"title":"Mabtis && MybatisPlus","slug":"TechStack-MybatisPlus","date":"2022-07-21","updated":"2023-11-06","path":"api/posts/31024.json","excerpt":"<blockquote><p> 总结了 Mabtis 和 plus 的一些小细节的知识 </p></blockquote>","cover":null,"content":null,"min2read":1,"word4post":318,"url":"/posts/31024/","categories":[{"name":"TechStack","path":"api/categories/TechStack.json","url":"/categories/TechStack/"}],"tags":[{"name":"Mabtis","path":"api/tags/Mabtis.json","url":"/tags/Mabtis/"}]}]}